Workbook
Name AbsentPct: Inputs!$B$26
Name AllowancePct: Inputs!$B$24
Name CompareTop: Dashboard!$A$15
Name DemandMult: Inputs!$B$6
Name EffShare: Inputs!$B$27
Name FlexFactor: Inputs!$B$37
Name FlexWage: Inputs!$B$42
Name IndirectPct: Inputs!$B$25
Name KPI_Cost: Dashboard!$B$5
Name KPI_CPU: Dashboard!$B$6
Name KPI_FlexDays: Dashboard!$B$9
Name KPI_FlexHC: Dashboard!$B$8
Name KPI_OT: Dashboard!$B$7
Name KPI_Units: Dashboard!$B$4
Name KPI_Util: Dashboard!$B$10
Name OTCapHrs: Inputs!$B$34
Name OTEff: Inputs!$B$36
Name OTMult: Inputs!$B$41
Name OTTakeUp: Inputs!$B$35
Name Roster: Inputs!$B$30
Name Scenario: Inputs!$B$5
Name ScenMult: Inputs!$B$10:$B$12
Name ScenName: Inputs!$A$10:$A$12
Name Share_Pack: Inputs!$B$18
Name Share_Pick: Inputs!$B$17
Name Share_Ship: Inputs!$B$19
Name Share_Stow: Inputs!$B$16
Name ShareA: Inputs!$B$45
Name ShareB: Inputs!$B$46
Name ShareC: Inputs!$B$47
Name ShiftHrs: Inputs!$B$23
Name UPH_Pack: Inputs!$C$18
Name UPH_Pick: Inputs!$C$17
Name UPH_Ship: Inputs!$C$19
Name UPH_Stow: Inputs!$C$16
Name Wage: Inputs!$B$40
Name WorkDays: Inputs!$B$31

Sheet Dashboard
A1: Fulfilment labour plan: 8-week view
A2: ="Scenario: "&Scenario&" | demand x"&TEXT(DemandMult,"0.00")&" | roster "&Roster&" permanent associates" -> 0
D3: Buttons run the macros in modLabourPlan.bas: import it once (Alt+F11, File, Import) and save as .xlsm.
A4: Units shipped | B4: =SUM(Plan!$E$5:$E$60) -> 0
A5: Total labour cost | B5: =SUM(Plan!$W$5:$W$60) -> 0
A6: Cost per unit | B6: =KPI_Cost/KPI_Units -> 0
A7: Overtime paid hours | B7: =SUM(Plan!$O$5:$O$60) -> 0
A8: Peak flex hires (one day) | B8: =MAX(Plan!$R$5:$R$60) -> 0
A9: Days needing flex | B9: =COUNTIF(Plan!$R$5:$R$60,">0") -> 0
A10: Average utilisation of roster | B10: =AVERAGE(Plan!$Y$5:$Y$60) -> 0
A12: Scenario comparison
A13: Refreshed by macro CompareScenarios. Values shown were calculated with the delivered inputs; re-run after changing Inputs.
A14: Scenario | B14: Units | C14: Total cost | D14: Cost per unit | E14: OT paid hrs | F14: Peak flex HC | G14: Days needing flex | H14: Avg utilisation
A15: Base | B15: 3088100 | C15: 10238039 | D15: 3.3153198 | E15: 3583.7951 | F15: 50 | G15: 16 | H15: 0.92832989
A16: Peak | B16: 4014530 | C16: 13631300 | D16: 3.3954909 | E16: 8934.7003 | F16: 137 | G16: 46 | H16: 0.9872492
A17: Low | B17: 2624885 | C17: 9346693.2 | D17: 3.560801 | E17: 990.0662 | F17: 7 | G17: 1 | H17: 0.83662522

Sheet Inputs
A1: Inputs and assumptions
A2: All figures are illustrative planning assumptions for a generic fulfilment centre, not data from any real site. Blue cells are inputs.
A4: Scenario
A5: Scenario (dropdown) | B5: Base | D5: Base, Peak or Low. Scales the forecast. The scenario buttons on the Dashboard set it too.
A6: Demand multiplier (from table) | B6: =INDEX(ScenMult,MATCH(Scenario,ScenName,0)) -> 0
A8: Scenario table
A9: Scenario | B9: Multiplier
A10: Base | B10: 1
A11: Peak | B11: 1.3
A12: Low | B12: 0.85
A14: Process standards
A15: Process | B15: Units per outbound unit | C15: UPH | D15: UPH = units handled per productive labour hour.
A16: Stow | B16: 0.9 | C16: 250
A17: Pick | B17: 1 | C17: 100
A18: Pack | B18: 1 | C18: 120
A19: Ship | B19: 1 | C19: 300
D20: Stow at 0.90: inbound stow volume runs a little below outbound units.
A22: Shift and shrinkage
A23: Paid shift length | B23: 9 | C23: hours | D23: Paid hours per associate per working day.
A24: Breaks and allowances | B24: 0.1 | C24: % of shift | D24: Paid time not spent on standard work (breaks, PPE, handover).
A25: Indirect / training time | B25: 0.05 | C25: % of shift | D25: Meetings, training, 5S.
A26: Absenteeism | B26: 0.08 | C26: % of roster | D26: Unplanned absence; absent associates are unpaid.
A27: Productive share of paid hours | B27: =(1-AllowancePct)*(1-IndirectPct) -> 0 | D27: Calculated.
A29: Permanent workforce
A30: Permanent roster | B30: 230 | C30: associates | D30: Cross-trained pool, assumed deployable to any process.
A31: Working days per week | B31: 6 | C31: days | D31: Weekly off is rotated; average daily availability = roster x days / 7.
A33: Overtime and flex labour
A34: Max overtime per associate per day | B34: 2 | C34: hours | D34: Cap on OT hours a present associate can work.
A35: Overtime take-up | B35: 0.5 | C35: % of present | D35: Share of present associates who will take OT.
A36: Overtime productivity | B36: 0.9 | C36: x | D36: Productive hours per paid OT hour.
A37: Flex productivity vs permanent | B37: 0.85 | C37: x | D37: Seasonal hires are slower in the first weeks.
A39: Cost
A40: Permanent wage | B40: 100 | C40: INR / paid hr | D40: Fully loaded, illustrative.
A41: Overtime multiplier | B41: 2 | C41: x wage | D41: Double rate, as under the Factories Act.
A42: Flex / agency wage | B42: 120 | C42: INR / paid hr | D42: Includes agency margin.
A44: Shift split of attending headcount
A45: Shift A (morning) | B45: 0.45 | C45: % | D45: Must total 100%.
A46: Shift B (afternoon) | B46: 0.4 | C46: %
A47: Shift C (night) | B47: 0.15 | C47: %

Sheet Plan
A1: Daily labour plan
A2: Rows are formulas driven by Inputs. Permanent labour is used first, then overtime, then flex hires.
A4: Date | B4: Day | C4: Week | D4: Base forecast (units) | E4: Scenario units | F4: Stow hrs | G4: Pick hrs | H4: Pack hrs | I4: Ship hrs | J4: Required productive hrs | K4: Required HC (rostered) | L4: Permanent HC on roster | M4: Permanent productive hrs | N4: Shortfall hrs | O4: OT paid hrs | P4: OT productive hrs | Q4: Flex productive hrs needed | R4: Flex HC | S4: Flex paid hrs | T4: Regular cost | U4: OT cost | V4: Flex cost | W4: Total cost | X4: Cost per unit | Y4: Utilisation | Z4: Action
A5: 46328 | B5: =TEXT(A5,"ddd") -> 0 | C5: =INT((A5-$A$5)/7)+1 -> 0 | D5: 53320 | E5: =D5*DemandMult -> 0 | F5: =E5*Share_Stow/UPH_Stow -> 0 | G5: =E5*Share_Pick/UPH_Pick -> 0 | H5: =E5*Share_Pack/UPH_Pack -> 0 | I5: =E5*Share_Ship/UPH_Ship -> 0 | J5: =SUM(F5:I5) -> 0 | K5: =J5/(ShiftHrs*EffShare)/(1-AbsentPct) -> 0 | L5: =Roster*WorkDays/7 -> 0 | M5: =L5*(1-AbsentPct)*ShiftHrs*EffShare -> 0 | N5: =MAX(0,J5-M5) -> 0 | O5: =MIN(N5/OTEff,L5*(1-AbsentPct)*OTCapHrs*OTTakeUp) -> 0 | P5: =O5*OTEff -> 0 | Q5: =MAX(0,N5-P5) -> 0 | R5: =ROUNDUP(ROUND(Q5/(ShiftHrs*EffShare*FlexFactor),9),0) -> 0 | S5: =R5*ShiftHrs -> 0 | T5: =L5*(1-AbsentPct)*ShiftHrs*Wage -> 0 | U5: =O5*Wage*OTMult -> 0 | V5: =S5*FlexWage -> 0 | W5: =SUM(T5:V5) -> 0 | X5: =W5/E5 -> 0 | Y5: =MIN(J5,M5)/M5 -> 0 | Z5: =IF(R5>0,"Flex hire",IF(O5>0,"Overtime","Roster covers")) -> 0
A6: 46329 | B6: =TEXT(A6,"ddd") -> 0 | C6: =INT((A6-$A$5)/7)+1 -> 0 | D6: 48910 | E6: =D6*DemandMult -> 0 | F6: =E6*Share_Stow/UPH_Stow -> 0 | G6: =E6*Share_Pick/UPH_Pick -> 0 | H6: =E6*Share_Pack/UPH_Pack -> 0 | I6: =E6*Share_Ship/UPH_Ship -> 0 | J6: =SUM(F6:I6) -> 0 | K6: =J6/(ShiftHrs*EffShare)/(1-AbsentPct) -> 0 | L6: =Roster*WorkDays/7 -> 0 | M6: =L6*(1-AbsentPct)*ShiftHrs*EffShare -> 0 | N6: =MAX(0,J6-M6) -> 0 | O6: =MIN(N6/OTEff,L6*(1-AbsentPct)*OTCapHrs*OTTakeUp) -> 0 | P6: =O6*OTEff -> 0 | Q6: =MAX(0,N6-P6) -> 0 | R6: =ROUNDUP(ROUND(Q6/(ShiftHrs*EffShare*FlexFactor),9),0) -> 0 | S6: =R6*ShiftHrs -> 0 | T6: =L6*(1-AbsentPct)*ShiftHrs*Wage -> 0 | U6: =O6*Wage*OTMult -> 0 | V6: =S6*FlexWage -> 0 | W6: =SUM(T6:V6) -> 0 | X6: =W6/E6 -> 0 | Y6: =MIN(J6,M6)/M6 -> 0 | Z6: =IF(R6>0,"Flex hire",IF(O6>0,"Overtime","Roster covers")) -> 0
A7: 46330 | B7: =TEXT(A7,"ddd") -> 0 | C7: =INT((A7-$A$5)/7)+1 -> 0 | D7: 50100 | E7: =D7*DemandMult -> 0 | F7: =E7*Share_Stow/UPH_Stow -> 0 | G7: =E7*Share_Pick/UPH_Pick -> 0 | H7: =E7*Share_Pack/UPH_Pack -> 0 | I7: =E7*Share_Ship/UPH_Ship -> 0 | J7: =SUM(F7:I7) -> 0 | K7: =J7/(ShiftHrs*EffShare)/(1-AbsentPct) -> 0 | L7: =Roster*WorkDays/7 -> 0 | M7: =L7*(1-AbsentPct)*ShiftHrs*EffShare -> 0 | N7: =MAX(0,J7-M7) -> 0 | O7: =MIN(N7/OTEff,L7*(1-AbsentPct)*OTCapHrs*OTTakeUp) -> 0 | P7: =O7*OTEff -> 0 | Q7: =MAX(0,N7-P7) -> 0 | R7: =ROUNDUP(ROUND(Q7/(ShiftHrs*EffShare*FlexFactor),9),0) -> 0 | S7: =R7*ShiftHrs -> 0 | T7: =L7*(1-AbsentPct)*ShiftHrs*Wage -> 0 | U7: =O7*Wage*OTMult -> 0 | V7: =S7*FlexWage -> 0 | W7: =SUM(T7:V7) -> 0 | X7: =W7/E7 -> 0 | Y7: =MIN(J7,M7)/M7 -> 0 | Z7: =IF(R7>0,"Flex hire",IF(O7>0,"Overtime","Roster covers")) -> 0
A8: 46331 | B8: =TEXT(A8,"ddd") -> 0 | C8: =INT((A8-$A$5)/7)+1 -> 0 | D8: 48390 | E8: =D8*DemandMult -> 0 | F8: =E8*Share_Stow/UPH_Stow -> 0 | G8: =E8*Share_Pick/UPH_Pick -> 0 | H8: =E8*Share_Pack/UPH_Pack -> 0 | I8: =E8*Share_Ship/UPH_Ship -> 0 | J8: =SUM(F8:I8) -> 0 | K8: =J8/(ShiftHrs*EffShare)/(1-AbsentPct) -> 0 | L8: =Roster*WorkDays/7 -> 0 | M8: =L8*(1-AbsentPct)*ShiftHrs*EffShare -> 0 | N8: =MAX(0,J8-M8) -> 0 | O8: =MIN(N8/OTEff,L8*(1-AbsentPct)*OTCapHrs*OTTakeUp) -> 0 | P8: =O8*OTEff -> 0 | Q8: =MAX(0,N8-P8) -> 0 | R8: =ROUNDUP(ROUND(Q8/(ShiftHrs*EffShare*FlexFactor),9),0) -> 0 | S8: =R8*ShiftHrs -> 0 | T8: =L8*(1-AbsentPct)*ShiftHrs*Wage -> 0 | U8: =O8*Wage*OTMult -> 0 | V8: =S8*FlexWage -> 0 | W8: =SUM(T8:V8) -> 0 | X8: =W8/E8 -> 0 | Y8: =MIN(J8,M8)/M8 -> 0 | Z8: =IF(R8>0,"Flex hire",IF(O8>0,"Overtime","Roster covers")) -> 0
A9: 46332 | B9: =TEXT(A9,"ddd") -> 0 | C9: =INT((A9-$A$5)/7)+1 -> 0 | D9: 54910 | E9: =D9*DemandMult -> 0 | F9: =E9*Share_Stow/UPH_Stow -> 0 | G9: =E9*Share_Pick/UPH_Pick -> 0 | H9: =E9*Share_Pack/UPH_Pack -> 0 | I9: =E9*Share_Ship/UPH_Ship -> 0 | J9: =SUM(F9:I9) -> 0 | K9: =J9/(ShiftHrs*EffShare)/(1-AbsentPct) -> 0 | L9: =Roster*WorkDays/7 -> 0 | M9: =L9*(1-AbsentPct)*ShiftHrs*EffShare -> 0 | N9: =MAX(0,J9-M9) -> 0 | O9: =MIN(N9/OTEff,L9*(1-AbsentPct)*OTCapHrs*OTTakeUp) -> 0 | P9: =O9*OTEff -> 0 | Q9: =MAX(0,N9-P9) -> 0 | R9: =ROUNDUP(ROUND(Q9/(ShiftHrs*EffShare*FlexFactor),9),0) -> 0 | S9: =R9*ShiftHrs -> 0 | T9: =L9*(1-AbsentPct)*ShiftHrs*Wage -> 0 | U9: =O9*Wage*OTMult -> 0 | V9: =S9*FlexWage -> 0 | W9: =SUM(T9:V9) -> 0 | X9: =W9/E9 -> 0 | Y9: =MIN(J9,M9)/M9 -> 0 | Z9: =IF(R9>0,"Flex hire",IF(O9>0,"Overtime","Roster covers")) -> 0
A10: 46333 | B10: =TEXT(A10,"ddd") -> 0 | C10: =INT((A10-$A$5)/7)+1 -> 0 | D10: 45570 | E10: =D10*DemandMult -> 0 | F10: =E10*Share_Stow/UPH_Stow -> 0 | G10: =E10*Share_Pick/UPH_Pick -> 0 | H10: =E10*Share_Pack/UPH_Pack -> 0 | I10: =E10*Share_Ship/UPH_Ship -> 0 | J10: =SUM(F10:I10) -> 0 | K10: =J10/(ShiftHrs*EffShare)/(1-AbsentPct) -> 0 | L10: =Roster*WorkDays/7 -> 0 | M10: =L10*(1-AbsentPct)*ShiftHrs*EffShare -> 0 | N10: =MAX(0,J10-M10) -> 0 | O10: =MIN(N10/OTEff,L10*(1-AbsentPct)*OTCapHrs*OTTakeUp) -> 0 | P10: =O10*OTEff -> 0 | Q10: =MAX(0,N10-P10) -> 0 | R10: =ROUNDUP(ROUND(Q10/(ShiftHrs*EffShare*FlexFactor),9),0) -> 0 | S10: =R10*ShiftHrs -> 0 | T10: =L10*(1-AbsentPct)*ShiftHrs*Wage -> 0 | U10: =O10*Wage*OTMult -> 0 | V10: =S10*FlexWage -> 0 | W10: =SUM(T10:V10) -> 0 | X10: =W10/E10 -> 0 | Y10: =MIN(J10,M10)/M10 -> 0 | Z10: =IF(R10>0,"Flex hire",IF(O10>0,"Overtime","Roster covers")) -> 0
A11: 46334 | B11: =TEXT(A11,"ddd") -> 0 | C11: =INT((A11-$A$5)/7)+1 -> 0 | D11: 35370 | E11: =D11*DemandMult -> 0 | F11: =E11*Share_Stow/UPH_Stow -> 0 | G11: =E11*Share_Pick/UPH_Pick -> 0 | H11: =E11*Share_Pack/UPH_Pack -> 0 | I11: =E11*Share_Ship/UPH_Ship -> 0 | J11: =SUM(F11:I11) -> 0 | K11: =J11/(ShiftHrs*EffShare)/(1-AbsentPct) -> 0 | L11: =Roster*WorkDays/7 -> 0 | M11: =L11*(1-AbsentPct)*ShiftHrs*EffShare -> 0 | N11: =MAX(0,J11-M11) -> 0 | O11: =MIN(N11/OTEff,L11*(1-AbsentPct)*OTCapHrs*OTTakeUp) -> 0 | P11: =O11*OTEff -> 0 | Q11: =MAX(0,N11-P11) -> 0 | R11: =ROUNDUP(ROUND(Q11/(ShiftHrs*EffShare*FlexFactor),9),0) -> 0 | S11: =R11*ShiftHrs -> 0 | T11: =L11*(1-AbsentPct)*ShiftHrs*Wage -> 0 | U11: =O11*Wage*OTMult -> 0 | V11: =S11*FlexWage -> 0 | W11: =SUM(T11:V11) -> 0 | X11: =W11/E11 -> 0 | Y11: =MIN(J11,M11)/M11 -> 0 | Z11: =IF(R11>0,"Flex hire",IF(O11>0,"Overtime","Roster covers")) -> 0
A12: 46335 | B12: =TEXT(A12,"ddd") -> 0 | C12: =INT((A12-$A$5)/7)+1 -> 0 | D12: 55190 | E12: =D12*DemandMult -> 0 | F12: =E12*Share_Stow/UPH_Stow -> 0 | G12: =E12*Share_Pick/UPH_Pick -> 0 | H12: =E12*Share_Pack/UPH_Pack -> 0 | I12: =E12*Share_Ship/UPH_Ship -> 0 | J12: =SUM(F12:I12) -> 0 | K12: =J12/(ShiftHrs*EffShare)/(1-AbsentPct) -> 0 | L12: =Roster*WorkDays/7 -> 0 | M12: =L12*(1-AbsentPct)*ShiftHrs*EffShare -> 0 | N12: =MAX(0,J12-M12) -> 0 | O12: =MIN(N12/OTEff,L12*(1-AbsentPct)*OTCapHrs*OTTakeUp) -> 0 | P12: =O12*OTEff -> 0 | Q12: =MAX(0,N12-P12) -> 0 | R12: =ROUNDUP(ROUND(Q12/(ShiftHrs*EffShare*FlexFactor),9),0) -> 0 | S12: =R12*ShiftHrs -> 0 | T12: =L12*(1-AbsentPct)*ShiftHrs*Wage -> 0 | U12: =O12*Wage*OTMult -> 0 | V12: =S12*FlexWage -> 0 | W12: =SUM(T12:V12) -> 0 | X12: =W12/E12 -> 0 | Y12: =MIN(J12,M12)/M12 -> 0 | Z12: =IF(R12>0,"Flex hire",IF(O12>0,"Overtime","Roster covers")) -> 0
A13: 46336 | B13: =TEXT(A13,"ddd") -> 0 | C13: =INT((A13-$A$5)/7)+1 -> 0 | D13: 54180 | E13: =D13*DemandMult -> 0 | F13: =E13*Share_Stow/UPH_Stow -> 0 | G13: =E13*Share_Pick/UPH_Pick -> 0 | H13: =E13*Share_Pack/UPH_Pack -> 0 | I13: =E13*Share_Ship/UPH_Ship -> 0 | J13: =SUM(F13:I13) -> 0 | K13: =J13/(ShiftHrs*EffShare)/(1-AbsentPct) -> 0 | L13: =Roster*WorkDays/7 -> 0 | M13: =L13*(1-AbsentPct)*ShiftHrs*EffShare -> 0 | N13: =MAX(0,J13-M13) -> 0 | O13: =MIN(N13/OTEff,L13*(1-AbsentPct)*OTCapHrs*OTTakeUp) -> 0 | P13: =O13*OTEff -> 0 | Q13: =MAX(0,N13-P13) -> 0 | R13: =ROUNDUP(ROUND(Q13/(ShiftHrs*EffShare*FlexFactor),9),0) -> 0 | S13: =R13*ShiftHrs -> 0 | T13: =L13*(1-AbsentPct)*ShiftHrs*Wage -> 0 | U13: =O13*Wage*OTMult -> 0 | V13: =S13*FlexWage -> 0 | W13: =SUM(T13:V13) -> 0 | X13: =W13/E13 -> 0 | Y13: =MIN(J13,M13)/M13 -> 0 | Z13: =IF(R13>0,"Flex hire",IF(O13>0,"Overtime","Roster covers")) -> 0
A14: 46337 | B14: =TEXT(A14,"ddd") -> 0 | C14: =INT((A14-$A$5)/7)+1 -> 0 | D14: 53560 | E14: =D14*DemandMult -> 0 | F14: =E14*Share_Stow/UPH_Stow -> 0 | G14: =E14*Share_Pick/UPH_Pick -> 0 | H14: =E14*Share_Pack/UPH_Pack -> 0 | I14: =E14*Share_Ship/UPH_Ship -> 0 | J14: =SUM(F14:I14) -> 0 | K14: =J14/(ShiftHrs*EffShare)/(1-AbsentPct) -> 0 | L14: =Roster*WorkDays/7 -> 0 | M14: =L14*(1-AbsentPct)*ShiftHrs*EffShare -> 0 | N14: =MAX(0,J14-M14) -> 0 | O14: =MIN(N14/OTEff,L14*(1-AbsentPct)*OTCapHrs*OTTakeUp) -> 0 | P14: =O14*OTEff -> 0 | Q14: =MAX(0,N14-P14) -> 0 | R14: =ROUNDUP(ROUND(Q14/(ShiftHrs*EffShare*FlexFactor),9),0) -> 0 | S14: =R14*ShiftHrs -> 0 | T14: =L14*(1-AbsentPct)*ShiftHrs*Wage -> 0 | U14: =O14*Wage*OTMult -> 0 | V14: =S14*FlexWage -> 0 | W14: =SUM(T14:V14) -> 0 | X14: =W14/E14 -> 0 | Y14: =MIN(J14,M14)/M14 -> 0 | Z14: =IF(R14>0,"Flex hire",IF(O14>0,"Overtime","Roster covers")) -> 0
A15: 46338 | B15: =TEXT(A15,"ddd") -> 0 | C15: =INT((A15-$A$5)/7)+1 -> 0 | D15: 51190 | E15: =D15*DemandMult -> 0 | F15: =E15*Share_Stow/UPH_Stow -> 0 | G15: =E15*Share_Pick/UPH_Pick -> 0 | H15: =E15*Share_Pack/UPH_Pack -> 0 | I15: =E15*Share_Ship/UPH_Ship -> 0 | J15: =SUM(F15:I15) -> 0 | K15: =J15/(ShiftHrs*EffShare)/(1-AbsentPct) -> 0 | L15: =Roster*WorkDays/7 -> 0 | M15: =L15*(1-AbsentPct)*ShiftHrs*EffShare -> 0 | N15: =MAX(0,J15-M15) -> 0 | O15: =MIN(N15/OTEff,L15*(1-AbsentPct)*OTCapHrs*OTTakeUp) -> 0 | P15: =O15*OTEff -> 0 | Q15: =MAX(0,N15-P15) -> 0 | R15: =ROUNDUP(ROUND(Q15/(ShiftHrs*EffShare*FlexFactor),9),0) -> 0 | S15: =R15*ShiftHrs -> 0 | T15: =L15*(1-AbsentPct)*ShiftHrs*Wage -> 0 | U15: =O15*Wage*OTMult -> 0 | V15: =S15*FlexWage -> 0 | W15: =SUM(T15:V15) -> 0 | X15: =W15/E15 -> 0 | Y15: =MIN(J15,M15)/M15 -> 0 | Z15: =IF(R15>0,"Flex hire",IF(O15>0,"Overtime","Roster covers")) -> 0
A16: 46339 | B16: =TEXT(A16,"ddd") -> 0 | C16: =INT((A16-$A$5)/7)+1 -> 0 | D16: 55610 | E16: =D16*DemandMult -> 0 | F16: =E16*Share_Stow/UPH_Stow -> 0 | G16: =E16*Share_Pick/UPH_Pick -> 0 | H16: =E16*Share_Pack/UPH_Pack -> 0 | I16: =E16*Share_Ship/UPH_Ship -> 0 | J16: =SUM(F16:I16) -> 0 | K16: =J16/(ShiftHrs*EffShare)/(1-AbsentPct) -> 0 | L16: =Roster*WorkDays/7 -> 0 | M16: =L16*(1-AbsentPct)*ShiftHrs*EffShare -> 0 | N16: =MAX(0,J16-M16) -> 0 | O16: =MIN(N16/OTEff,L16*(1-AbsentPct)*OTCapHrs*OTTakeUp) -> 0 | P16: =O16*OTEff -> 0 | Q16: =MAX(0,N16-P16) -> 0 | R16: =ROUNDUP(ROUND(Q16/(ShiftHrs*EffShare*FlexFactor),9),0) -> 0 | S16: =R16*ShiftHrs -> 0 | T16: =L16*(1-AbsentPct)*ShiftHrs*Wage -> 0 | U16: =O16*Wage*OTMult -> 0 | V16: =S16*FlexWage -> 0 | W16: =SUM(T16:V16) -> 0 | X16: =W16/E16 -> 0 | Y16: =MIN(J16,M16)/M16 -> 0 | Z16: =IF(R16>0,"Flex hire",IF(O16>0,"Overtime","Roster covers")) -> 0
... A60: 46383 | B60: =TEXT(A60,"ddd") -> 0 | C60: =INT((A60-$A$5)/7)+1 -> 0 | D60: 33190 | E60: =D60*DemandMult -> 0 | F60: =E60*Share_Stow/UPH_Stow -> 0 | G60: =E60*Share_Pick/UPH_Pick -> 0 | H60: =E60*Share_Pack/UPH_Pack -> 0 | I60: =E60*Share_Ship/UPH_Ship -> 0 | J60: =SUM(F60:I60) -> 0 | K60: =J60/(ShiftHrs*EffShare)/(1-AbsentPct) -> 0 | L60: =Roster*WorkDays/7 -> 0 | M60: =L60*(1-AbsentPct)*ShiftHrs*EffShare -> 0 | N60: =MAX(0,J60-M60) -> 0 | O60: =MIN(N60/OTEff,L60*(1-AbsentPct)*OTCapHrs*OTTakeUp) -> 0 | P60: =O60*OTEff -> 0 | Q60: =MAX(0,N60-P60) -> 0 | R60: =ROUNDUP(ROUND(Q60/(ShiftHrs*EffShare*FlexFactor),9),0) -> 0 | S60: =R60*ShiftHrs -> 0 | T60: =L60*(1-AbsentPct)*ShiftHrs*Wage -> 0 | U60: =O60*Wage*OTMult -> 0 | V60: =S60*FlexWage -> 0 | W60: =SUM(T60:V60) -> 0 | X60: =W60/E60 -> 0 | Y60: =MIN(J60,M60)/M60 -> 0 | Z60: =IF(R60>0,"Flex hire",IF(O60>0,"Overtime","Roster covers")) -> 0

Sheet ShiftPlan
A1: Attending headcount by shift
A2: Permanent associates present (after absenteeism) plus flex hires, split by the shift shares on Inputs. Shift C is the balancing figure so rows add up.
A4: Date | B4: Day | C4: Permanent present | D4: Flex HC | E4: Total attending | F4: Shift A | G4: Shift B | H4: Shift C
A5: =Plan!A5 -> 0 | B5: =Plan!B5 -> 0 | C5: =Plan!L5*(1-AbsentPct) -> 0 | D5: =Plan!R5 -> 0 | E5: =C5+D5 -> 0 | F5: =ROUND(E5*ShareA,0) -> 0 | G5: =ROUND(E5*ShareB,0) -> 0 | H5: =ROUND(E5,0)-F5-G5 -> 0
A6: =Plan!A6 -> 0 | B6: =Plan!B6 -> 0 | C6: =Plan!L6*(1-AbsentPct) -> 0 | D6: =Plan!R6 -> 0 | E6: =C6+D6 -> 0 | F6: =ROUND(E6*ShareA,0) -> 0 | G6: =ROUND(E6*ShareB,0) -> 0 | H6: =ROUND(E6,0)-F6-G6 -> 0
A7: =Plan!A7 -> 0 | B7: =Plan!B7 -> 0 | C7: =Plan!L7*(1-AbsentPct) -> 0 | D7: =Plan!R7 -> 0 | E7: =C7+D7 -> 0 | F7: =ROUND(E7*ShareA,0) -> 0 | G7: =ROUND(E7*ShareB,0) -> 0 | H7: =ROUND(E7,0)-F7-G7 -> 0
A8: =Plan!A8 -> 0 | B8: =Plan!B8 -> 0 | C8: =Plan!L8*(1-AbsentPct) -> 0 | D8: =Plan!R8 -> 0 | E8: =C8+D8 -> 0 | F8: =ROUND(E8*ShareA,0) -> 0 | G8: =ROUND(E8*ShareB,0) -> 0 | H8: =ROUND(E8,0)-F8-G8 -> 0
A9: =Plan!A9 -> 0 | B9: =Plan!B9 -> 0 | C9: =Plan!L9*(1-AbsentPct) -> 0 | D9: =Plan!R9 -> 0 | E9: =C9+D9 -> 0 | F9: =ROUND(E9*ShareA,0) -> 0 | G9: =ROUND(E9*ShareB,0) -> 0 | H9: =ROUND(E9,0)-F9-G9 -> 0
A10: =Plan!A10 -> 0 | B10: =Plan!B10 -> 0 | C10: =Plan!L10*(1-AbsentPct) -> 0 | D10: =Plan!R10 -> 0 | E10: =C10+D10 -> 0 | F10: =ROUND(E10*ShareA,0) -> 0 | G10: =ROUND(E10*ShareB,0) -> 0 | H10: =ROUND(E10,0)-F10-G10 -> 0
A11: =Plan!A11 -> 0 | B11: =Plan!B11 -> 0 | C11: =Plan!L11*(1-AbsentPct) -> 0 | D11: =Plan!R11 -> 0 | E11: =C11+D11 -> 0 | F11: =ROUND(E11*ShareA,0) -> 0 | G11: =ROUND(E11*ShareB,0) -> 0 | H11: =ROUND(E11,0)-F11-G11 -> 0
A12: =Plan!A12 -> 0 | B12: =Plan!B12 -> 0 | C12: =Plan!L12*(1-AbsentPct) -> 0 | D12: =Plan!R12 -> 0 | E12: =C12+D12 -> 0 | F12: =ROUND(E12*ShareA,0) -> 0 | G12: =ROUND(E12*ShareB,0) -> 0 | H12: =ROUND(E12,0)-F12-G12 -> 0
A13: =Plan!A13 -> 0 | B13: =Plan!B13 -> 0 | C13: =Plan!L13*(1-AbsentPct) -> 0 | D13: =Plan!R13 -> 0 | E13: =C13+D13 -> 0 | F13: =ROUND(E13*ShareA,0) -> 0 | G13: =ROUND(E13*ShareB,0) -> 0 | H13: =ROUND(E13,0)-F13-G13 -> 0
A14: =Plan!A14 -> 0 | B14: =Plan!B14 -> 0 | C14: =Plan!L14*(1-AbsentPct) -> 0 | D14: =Plan!R14 -> 0 | E14: =C14+D14 -> 0 | F14: =ROUND(E14*ShareA,0) -> 0 | G14: =ROUND(E14*ShareB,0) -> 0 | H14: =ROUND(E14,0)-F14-G14 -> 0
A15: =Plan!A15 -> 0 | B15: =Plan!B15 -> 0 | C15: =Plan!L15*(1-AbsentPct) -> 0 | D15: =Plan!R15 -> 0 | E15: =C15+D15 -> 0 | F15: =ROUND(E15*ShareA,0) -> 0 | G15: =ROUND(E15*ShareB,0) -> 0 | H15: =ROUND(E15,0)-F15-G15 -> 0
A16: =Plan!A16 -> 0 | B16: =Plan!B16 -> 0 | C16: =Plan!L16*(1-AbsentPct) -> 0 | D16: =Plan!R16 -> 0 | E16: =C16+D16 -> 0 | F16: =ROUND(E16*ShareA,0) -> 0 | G16: =ROUND(E16*ShareB,0) -> 0 | H16: =ROUND(E16,0)-F16-G16 -> 0
... A60: =Plan!A60 -> 0 | B60: =Plan!B60 -> 0 | C60: =Plan!L60*(1-AbsentPct) -> 0 | D60: =Plan!R60 -> 0 | E60: =C60+D60 -> 0 | F60: =ROUND(E60*ShareA,0) -> 0 | G60: =ROUND(E60*ShareB,0) -> 0 | H60: =ROUND(E60,0)-F60-G60 -> 0

Sheet Weekly
A1: Weekly summary
A4: Week | B4: Starts | C4: Units | D4: Avg required HC | E4: Peak required HC | F4: Peak flex HC | G4: OT paid hrs | H4: Flex paid hrs | I4: Total cost | J4: Cost per unit
A5: 1 | B5: =Plan!$A$5+7*(A5-1) -> 0 | C5: =SUMIFS(Plan!$E$5:$E$60,Plan!$C$5:$C$60,A5) -> 0 | D5: =AVERAGEIFS(Plan!$K$5:$K$60,Plan!$C$5:$C$60,A5) -> 0 | E5: =_xlfn.MAXIFS(Plan!$K$5:$K$60,Plan!$C$5:$C$60,A5) -> 0 | F5: =_xlfn.MAXIFS(Plan!$R$5:$R$60,Plan!$C$5:$C$60,A5) -> 0 | G5: =SUMIFS(Plan!$O$5:$O$60,Plan!$C$5:$C$60,A5) -> 0 | H5: =SUMIFS(Plan!$S$5:$S$60,Plan!$C$5:$C$60,A5) -> 0 | I5: =SUMIFS(Plan!$W$5:$W$60,Plan!$C$5:$C$60,A5) -> 0 | J5: =I5/C5 -> 0
A6: 2 | B6: =Plan!$A$5+7*(A6-1) -> 0 | C6: =SUMIFS(Plan!$E$5:$E$60,Plan!$C$5:$C$60,A6) -> 0 | D6: =AVERAGEIFS(Plan!$K$5:$K$60,Plan!$C$5:$C$60,A6) -> 0 | E6: =_xlfn.MAXIFS(Plan!$K$5:$K$60,Plan!$C$5:$C$60,A6) -> 0 | F6: =_xlfn.MAXIFS(Plan!$R$5:$R$60,Plan!$C$5:$C$60,A6) -> 0 | G6: =SUMIFS(Plan!$O$5:$O$60,Plan!$C$5:$C$60,A6) -> 0 | H6: =SUMIFS(Plan!$S$5:$S$60,Plan!$C$5:$C$60,A6) -> 0 | I6: =SUMIFS(Plan!$W$5:$W$60,Plan!$C$5:$C$60,A6) -> 0 | J6: =I6/C6 -> 0
A7: 3 | B7: =Plan!$A$5+7*(A7-1) -> 0 | C7: =SUMIFS(Plan!$E$5:$E$60,Plan!$C$5:$C$60,A7) -> 0 | D7: =AVERAGEIFS(Plan!$K$5:$K$60,Plan!$C$5:$C$60,A7) -> 0 | E7: =_xlfn.MAXIFS(Plan!$K$5:$K$60,Plan!$C$5:$C$60,A7) -> 0 | F7: =_xlfn.MAXIFS(Plan!$R$5:$R$60,Plan!$C$5:$C$60,A7) -> 0 | G7: =SUMIFS(Plan!$O$5:$O$60,Plan!$C$5:$C$60,A7) -> 0 | H7: =SUMIFS(Plan!$S$5:$S$60,Plan!$C$5:$C$60,A7) -> 0 | I7: =SUMIFS(Plan!$W$5:$W$60,Plan!$C$5:$C$60,A7) -> 0 | J7: =I7/C7 -> 0
A8: 4 | B8: =Plan!$A$5+7*(A8-1) -> 0 | C8: =SUMIFS(Plan!$E$5:$E$60,Plan!$C$5:$C$60,A8) -> 0 | D8: =AVERAGEIFS(Plan!$K$5:$K$60,Plan!$C$5:$C$60,A8) -> 0 | E8: =_xlfn.MAXIFS(Plan!$K$5:$K$60,Plan!$C$5:$C$60,A8) -> 0 | F8: =_xlfn.MAXIFS(Plan!$R$5:$R$60,Plan!$C$5:$C$60,A8) -> 0 | G8: =SUMIFS(Plan!$O$5:$O$60,Plan!$C$5:$C$60,A8) -> 0 | H8: =SUMIFS(Plan!$S$5:$S$60,Plan!$C$5:$C$60,A8) -> 0 | I8: =SUMIFS(Plan!$W$5:$W$60,Plan!$C$5:$C$60,A8) -> 0 | J8: =I8/C8 -> 0
A9: 5 | B9: =Plan!$A$5+7*(A9-1) -> 0 | C9: =SUMIFS(Plan!$E$5:$E$60,Plan!$C$5:$C$60,A9) -> 0 | D9: =AVERAGEIFS(Plan!$K$5:$K$60,Plan!$C$5:$C$60,A9) -> 0 | E9: =_xlfn.MAXIFS(Plan!$K$5:$K$60,Plan!$C$5:$C$60,A9) -> 0 | F9: =_xlfn.MAXIFS(Plan!$R$5:$R$60,Plan!$C$5:$C$60,A9) -> 0 | G9: =SUMIFS(Plan!$O$5:$O$60,Plan!$C$5:$C$60,A9) -> 0 | H9: =SUMIFS(Plan!$S$5:$S$60,Plan!$C$5:$C$60,A9) -> 0 | I9: =SUMIFS(Plan!$W$5:$W$60,Plan!$C$5:$C$60,A9) -> 0 | J9: =I9/C9 -> 0
A10: 6 | B10: =Plan!$A$5+7*(A10-1) -> 0 | C10: =SUMIFS(Plan!$E$5:$E$60,Plan!$C$5:$C$60,A10) -> 0 | D10: =AVERAGEIFS(Plan!$K$5:$K$60,Plan!$C$5:$C$60,A10) -> 0 | E10: =_xlfn.MAXIFS(Plan!$K$5:$K$60,Plan!$C$5:$C$60,A10) -> 0 | F10: =_xlfn.MAXIFS(Plan!$R$5:$R$60,Plan!$C$5:$C$60,A10) -> 0 | G10: =SUMIFS(Plan!$O$5:$O$60,Plan!$C$5:$C$60,A10) -> 0 | H10: =SUMIFS(Plan!$S$5:$S$60,Plan!$C$5:$C$60,A10) -> 0 | I10: =SUMIFS(Plan!$W$5:$W$60,Plan!$C$5:$C$60,A10) -> 0 | J10: =I10/C10 -> 0
A11: 7 | B11: =Plan!$A$5+7*(A11-1) -> 0 | C11: =SUMIFS(Plan!$E$5:$E$60,Plan!$C$5:$C$60,A11) -> 0 | D11: =AVERAGEIFS(Plan!$K$5:$K$60,Plan!$C$5:$C$60,A11) -> 0 | E11: =_xlfn.MAXIFS(Plan!$K$5:$K$60,Plan!$C$5:$C$60,A11) -> 0 | F11: =_xlfn.MAXIFS(Plan!$R$5:$R$60,Plan!$C$5:$C$60,A11) -> 0 | G11: =SUMIFS(Plan!$O$5:$O$60,Plan!$C$5:$C$60,A11) -> 0 | H11: =SUMIFS(Plan!$S$5:$S$60,Plan!$C$5:$C$60,A11) -> 0 | I11: =SUMIFS(Plan!$W$5:$W$60,Plan!$C$5:$C$60,A11) -> 0 | J11: =I11/C11 -> 0
A12: 8 | B12: =Plan!$A$5+7*(A12-1) -> 0 | C12: =SUMIFS(Plan!$E$5:$E$60,Plan!$C$5:$C$60,A12) -> 0 | D12: =AVERAGEIFS(Plan!$K$5:$K$60,Plan!$C$5:$C$60,A12) -> 0 | E12: =_xlfn.MAXIFS(Plan!$K$5:$K$60,Plan!$C$5:$C$60,A12) -> 0 | F12: =_xlfn.MAXIFS(Plan!$R$5:$R$60,Plan!$C$5:$C$60,A12) -> 0 | G12: =SUMIFS(Plan!$O$5:$O$60,Plan!$C$5:$C$60,A12) -> 0 | H12: =SUMIFS(Plan!$S$5:$S$60,Plan!$C$5:$C$60,A12) -> 0 | I12: =SUMIFS(Plan!$W$5:$W$60,Plan!$C$5:$C$60,A12) -> 0 | J12: =I12/C12 -> 0
